[
    {
        "name": "Heyzo 0386An Mukaiasianjapanesegirlpornteenmilfjav",
        "description": "",
        "code": "152022671_456243058",
        "img": "https://raw.githubusercontent.com/kstmm/data/master/image2/hdem5jmyWoo",
        "time": "4033"
    },
    {
        "name": "Heyzo 0397Aoi Yuukiasianjapanesegirlpornteenmilfjav",
        "description": "",
        "code": "152022671_456243059",
        "img": "https://raw.githubusercontent.com/kstmm/data/master/image2/zzFuNHxa38g",
        "time": "3952"
    },
    {
        "name": "Heyzo 0389Sakura Senaasianjapanesegirlpornteenmilfjav",
        "description": "",
        "code": "152022671_456243060",
        "img": "https://raw.githubusercontent.com/kstmm/data/master/image2/1yk-fSWgwzQ",
        "time": "4132"
    },
    {
        "name": "Heyzo 0375Miyu Kaneyamaasianjapanesegirlpornteenmilfjav",
        "description": "",
        "code": "152022671_456243061",
        "img": "https://raw.githubusercontent.com/kstmm/data/master/image2/RnU2JKE-43Q",
        "time": "3539"
    },
    {
        "name": "Heyzo 0399Mikuru Shiinaasianjapanesegirlpornteenmilfjav",
        "description": "",
        "code": "152022671_456243062",
        "img": "https://raw.githubusercontent.com/kstmm/data/master/image2/_XIvDWa40zQ",
        "time": "4268"
    },
    {
        "name": "Heyzo 0423Shiho KamiyamaAyumi NiikuraMiyu Nakayamaasianjapanesegirlpornmilf",
        "description": "",
        "code": "152022671_456243063",
        "img": "https://raw.githubusercontent.com/kstmm/data/master/image2/LBzqSRxv6AI",
        "time": "3124"
    },
    {
        "name": "Heyzo 0429Riko Miyaseasianjapanesegirlpornteenmilfjav",
        "description": "",
        "code": "152022671_456243064",
        "img": "https://raw.githubusercontent.com/kstmm/data/master/image2/mCLblbZKMDg",
        "time": "3063"
    },
    {
        "name": "Heyzo 0419Rin Hitomiasianjapanesegirlpornteenmilfjav",
        "description": "",
        "code": "152022671_456243065",
        "img": "https://raw.githubusercontent.com/kstmm/data/master/image2/F263lUYs_GU",
        "time": "3301"
    },
    {
        "name": "Heyzo 0415Nami Itoshinoasianjapanesegirlpornteenmilfjav",
        "description": "",
        "code": "152022671_456243066",
        "img": "https://raw.githubusercontent.com/kstmm/data/master/image2/iio5xku2XxA",
        "time": "3376"
    },
    {
        "name": "Heyzo 0404Hikariasianjapanesegirlpornteenmilfjav",
        "description": "",
        "code": "152022671_456243067",
        "img": "https://raw.githubusercontent.com/kstmm/data/master/image2/GQdF9i1p3NQ",
        "time": "3824"
    },
    {
        "name": "Heyzo 0414Reo Saionjiasianjapanesegirlpornteenmilfjav",
        "description": "",
        "code": "152022671_456243068",
        "img": "https://raw.githubusercontent.com/kstmm/data/master/image2/iVQTzGwKfCs",
        "time": "3574"
    },
    {
        "name": "Heyzo 0424Saki Sudoasianjapanesegirlpornteenmilfjav",
        "description": "",
        "code": "152022671_456243069",
        "img": "https://raw.githubusercontent.com/kstmm/data/master/image2/a7XyUfBuLmw",
        "time": "3610"
    },
    {
        "name": "Heyzo 0411Yuri SatoArisa Nakanoasianjapanesegirlpornteenmilfjav",
        "description": "",
        "code": "152022671_456243070",
        "img": "https://raw.githubusercontent.com/kstmm/data/master/image2/KDNlzjXU6mY",
        "time": "3773"
    },
    {
        "name": "Heyzo 0407Nao KojimaArisa Nakanoasianjapanesegirlpornteenmilfjav",
        "description": "",
        "code": "152022671_456243072",
        "img": "https://raw.githubusercontent.com/kstmm/data/master/image2/bUnonk2LM4o",
        "time": "4275"
    },
    {
        "name": "Heyzo 0408Yuu AsakuraArisa Nakanoasianjapanesegirlpornteenmilfjav",
        "description": "",
        "code": "152022671_456243073",
        "img": "https://raw.githubusercontent.com/kstmm/data/master/image2/aHG96SqrQmY",
        "time": "4101"
    },
    {
        "name": "Heyzo 0421Yuri SatoArisa Nakanoasianjapanesegirlpornteenmilfjav",
        "description": "",
        "code": "152022671_456243074",
        "img": "https://raw.githubusercontent.com/kstmm/data/master/image2/arqcFjA3B7Q",
        "time": "4012"
    },
    {
        "name": "Heyzo 0409MomohaArisa Nakanoasianjapanesegirlpornteenmilfjav",
        "description": "",
        "code": "152022671_456243075",
        "img": "https://raw.githubusercontent.com/kstmm/data/master/image2/B1eDBnFw_1U",
        "time": "4260"
    },
    {
        "name": "Heyzo 0430NatsumiArisa Nakanoasianjapanesegirlpornteenmilfjav",
        "description": "",
        "code": "152022671_456243076",
        "img": "https://raw.githubusercontent.com/kstmm/data/master/image2/ernlIVoLQtM",
        "time": "5015"
    },
    {
        "name": "Heyzo 0433Izumi Harunagaasianjapanesegirlpornteenmilfjav",
        "description": "",
        "code": "152022671_456243078",
        "img": "https://raw.githubusercontent.com/kstmm/data/master/image2/fzvnhXrCY7s",
        "time": "3252"
    },
    {
        "name": "Heyzo 0436Alice Ozawaasianjapanesegirlpornteenmilfjav",
        "description": "",
        "code": "152022671_456243079",
        "img": "https://raw.githubusercontent.com/kstmm/data/master/image2/gGPDJ-02hMI",
        "time": "3434"
    },
    {
        "name": "Heyzo 0437Chie Miyakeasianjapanesegirlpornteenmilfjav",
        "description": "",
        "code": "152022671_456243080",
        "img": "https://raw.githubusercontent.com/kstmm/data/master/image2/EN1iJ9wT1Pk",
        "time": "3531"
    },
    {
        "name": "Heyzo 0434Kaede Yuzukiasianjapanesegirlpornteenmilfjav",
        "description": "",
        "code": "152022671_456243081",
        "img": "https://raw.githubusercontent.com/kstmm/data/master/image2/0XUnOoVKw7Q",
        "time": "3799"
    },
    {
        "name": "Heyzo 0456Lauraasianjapanesegirlpornteenmilfjav",
        "description": "",
        "code": "152022671_456243082",
        "img": "https://raw.githubusercontent.com/kstmm/data/master/image2/E6DI2_Fj1XY",
        "time": "2930"
    },
    {
        "name": "Heyzo 0466Yuuna Mizukiasianjapanesegirlpornteenmilfjav",
        "description": "",
        "code": "152022671_456243083",
        "img": "https://raw.githubusercontent.com/kstmm/data/master/image2/AgWBDIBTjXk",
        "time": "2946"
    },
    {
        "name": "Heyzo 0451Emiri Aizawaasianjapanesegirlpornteenmilfjav",
        "description": "",
        "code": "152022671_456243084",
        "img": "https://raw.githubusercontent.com/kstmm/data/master/image2/pclfU8lx4So",
        "time": "3231"
    },
    {
        "name": "Heyzo 0439Ryu Enamiasianjapanesegirlpornteenmilfjav",
        "description": "",
        "code": "152022671_456243085",
        "img": "https://raw.githubusercontent.com/kstmm/data/master/image2/em8xqb_1NZQ",
        "time": "4254"
    },
    {
        "name": "Heyzo 0444Nami Itoshinoasianjapanesegirlpornteenmilfjav",
        "description": "",
        "code": "152022671_456243086",
        "img": "https://raw.githubusercontent.com/kstmm/data/master/image/pdOOxTaMvQY",
        "time": "3777"
    },
    {
        "name": "Heyzo 0457Airi Minamiasianjapanesegirlpornteenmilfjav",
        "description": "",
        "code": "152022671_456243087",
        "img": "https://raw.githubusercontent.com/kstmm/data/master/image/T8YZvsJ4vnM",
        "time": "3773"
    },
    {
        "name": "Heyzo 0464Maikaasianjapanesegirlpornteenmilfjav",
        "description": "",
        "code": "152022671_456243088",
        "img": "https://raw.githubusercontent.com/kstmm/data/master/image/9If07ESBR2Y",
        "time": "3675"
    },
    {
        "name": "Heyzo 0467Sakura Aida asianjapanesegirlpornteenmilfjav",
        "description": "",
        "code": "152022671_456243089",
        "img": "https://raw.githubusercontent.com/kstmm/data/master/image/2_57oe9yJ3c",
        "time": "3518"
    }
]