[
    {
        "name": "SSNI-388 Yua Mikami",
        "description": "",
        "code": "152022671_456245189",
        "img": "https://raw.githubusercontent.com/imovpro/pro/master/asia/image/FIOi06sOJ5U",
        "time": "7459"
    },
    {
        "name": "SSNI-322",
        "description": "",
        "code": "152022671_456245190",
        "img": "https://raw.githubusercontent.com/imovpro/pro/master/asia/image/OlNsUhPyv7E",
        "time": "7241"
    },
    {
        "name": "SSNI-473 Yua Mikami",
        "description": "",
        "code": "152022671_456245191",
        "img": "https://raw.githubusercontent.com/imovpro/pro/master/asia/image/7lJRgpRb4nE",
        "time": "7007"
    },
    {
        "name": "SSNI-454 Tsukasa Aoi",
        "description": "",
        "code": "152022671_456245192",
        "img": "https://raw.githubusercontent.com/imovpro/pro/master/asia/image/KOhGIP_VBJc",
        "time": "7136"
    },
    {
        "name": "SSNI-474 Tsukasa Aoi",
        "description": "",
        "code": "152022671_456245193",
        "img": "https://raw.githubusercontent.com/imovpro/pro/master/asia/image/L4qustFdrTI",
        "time": "8747"
    },
    {
        "name": "OFJE-208 Tsukasa Aoi",
        "description": "",
        "code": "152022671_456245194",
        "img": "https://raw.githubusercontent.com/imovpro/pro/master/asia/image/xzOKtc5fS7k",
        "time": "28734"
    },
    {
        "name": "SSNI-495 Tsukasa Aoi",
        "description": "",
        "code": "152022671_456245195",
        "img": "https://raw.githubusercontent.com/imovpro/pro/master/asia/image/K-EgudD9x90",
        "time": "9596"
    },
    {
        "name": "OAE-165 Tsukasa Aoi",
        "description": "",
        "code": "152022671_456245196",
        "img": "https://raw.githubusercontent.com/imovpro/pro/master/asia/image/wJWtq9FcuZQ",
        "time": "7104"
    },
    {
        "name": "SSNI-409 Yua Mikami",
        "description": "",
        "code": "152022671_456245197",
        "img": "https://raw.githubusercontent.com/imovpro/pro/master/asia/image/zhbVAoJvUh8",
        "time": "7904"
    },
    {
        "name": "SSNI-589 Yua Mikami",
        "description": "",
        "code": "152022671_456245198",
        "img": "https://raw.githubusercontent.com/imovpro/pro/master/asia/image/5ZiX0EjtsjY",
        "time": "8910"
    },
    {
        "name": "SSNI-542 Yua Mikami",
        "description": "",
        "code": "152022671_456245199",
        "img": "https://raw.githubusercontent.com/imovpro/pro/master/asia/image/Fi4R6FJZNtQ",
        "time": "9089"
    },
    {
        "name": "ssni-101 Yua Mikami",
        "description": "",
        "code": "152022671_456245200",
        "img": "https://raw.githubusercontent.com/imovpro/pro/master/asia/image/cn7UGUh1x-I",
        "time": "8940"
    },
    {
        "name": "snis800 Yua Mikami",
        "description": "",
        "code": "152022671_456245201",
        "img": "https://raw.githubusercontent.com/imovpro/pro/master/asia/image/6XDpG1wh9E0",
        "time": "8132"
    },
    {
        "name": "SSNI-054 Yua Mikami",
        "description": "",
        "code": "152022671_456245202",
        "img": "https://raw.githubusercontent.com/imovpro/pro/master/asia/image/8GW-Z7UtuWc",
        "time": "6965"
    },
    {
        "name": "SSNI-229 Yua Mikami",
        "description": "",
        "code": "152022671_456245203",
        "img": "https://raw.githubusercontent.com/imovpro/pro/master/asia/image/tfyqWBJ-1E4",
        "time": "9618"
    },
    {
        "name": "ssni-009 Yua Mikami",
        "description": "",
        "code": "152022671_456245204",
        "img": "https://raw.githubusercontent.com/imovpro/pro/master/asia/image/3CLnMn8c2XU",
        "time": "8442"
    },
    {
        "name": "SSNI-152 Yua Mikami",
        "description": "",
        "code": "152022671_456245205",
        "img": "https://raw.githubusercontent.com/imovpro/pro/master/asia/image/k0dQiEjku8k",
        "time": "9555"
    },
    {
        "name": "SNIS896 Yua Mikami",
        "description": "",
        "code": "152022671_456245206",
        "img": "https://raw.githubusercontent.com/imovpro/pro/master/asia/image/EQoauZMBu8w",
        "time": "7122"
    },
    {
        "name": "081019-881 1pon",
        "description": "",
        "code": "152022671_456245213",
        "img": "https://raw.githubusercontent.com/imovpro/pro/master/asia/image/qjQwSfKHXtI",
        "time": "3697"
    },
    {
        "name": "072619-003 caribpr",
        "description": "",
        "code": "152022671_456245214",
        "img": "https://raw.githubusercontent.com/imovpro/pro/master/asia/image/l4lDj_ulxAU",
        "time": "3805"
    },
    {
        "name": "072817-001 caribpr",
        "description": "",
        "code": "152022671_456245216",
        "img": "https://raw.githubusercontent.com/imovpro/pro/master/asia/image/gw8nxs6pKHs",
        "time": "4084"
    },
    {
        "name": "081419-982 carib",
        "description": "",
        "code": "152022671_456245219",
        "img": "https://raw.githubusercontent.com/imovpro/pro/master/asia/image/emeEto8sYtg",
        "time": "3711"
    },
    {
        "name": "092019-003 caribpr",
        "description": "",
        "code": "152022671_456245222",
        "img": "https://raw.githubusercontent.com/imovpro/pro/master/asia/image/fD5o0uQTdis",
        "time": "3881"
    },
    {
        "name": "100119_181",
        "description": "",
        "code": "152022671_456245223",
        "img": "https://raw.githubusercontent.com/imovpro/pro/master/asia/image/RdzhbIxhOtQ",
        "time": "3518"
    },
    {
        "name": "101119-001-carib-1080p",
        "description": "",
        "code": "152022671_456245224",
        "img": "https://raw.githubusercontent.com/imovpro/pro/master/asia/image/H76BebQzyDI",
        "time": "3783"
    },
    {
        "name": "091418-003 caribpr",
        "description": "",
        "code": "152022671_456245225",
        "img": "https://raw.githubusercontent.com/imovpro/pro/master/asia/image/_CVeUoxm2KA",
        "time": "4364"
    },
    {
        "name": "Pacopacomama 110619-202",
        "description": "",
        "code": "152022671_456245226",
        "img": "https://raw.githubusercontent.com/imovpro/pro/master/asia/image/z55bcv62wFM",
        "time": "3911"
    },
    {
        "name": "heyzo 2127",
        "description": "",
        "code": "152022671_456245227",
        "img": "https://raw.githubusercontent.com/imovpro/pro/master/asia/image/9v0RweFae5U",
        "time": "2962"
    },
    {
        "name": "heyzo 2092",
        "description": "",
        "code": "152022671_456245228",
        "img": "https://raw.githubusercontent.com/imovpro/pro/master/asia/image/4PxXjG7Wc-E",
        "time": "3699"
    },
    {
        "name": "090718-003 caribpr",
        "description": "",
        "code": "152022671_456245229",
        "img": "https://raw.githubusercontent.com/imovpro/pro/master/asia/image/kLiUuzsofik",
        "time": "8451"
    }
]